OptiHPLCHandler/__init__.py
OptiHPLCHandler/empower_api_core.py
OptiHPLCHandler/empower_detector_module_method.py
OptiHPLCHandler/empower_handler.py
OptiHPLCHandler/empower_instrument_method.py
OptiHPLCHandler/empower_module_method.py
OptiHPLCHandler/factories.py
OptiHPLCHandler/applications/__init__.py
OptiHPLCHandler/applications/generate_basic_robustness_methods.py
OptiHPLCHandler/applications/revert_method.py
OptiHPLCHandler/applications/empower_implementation/empower_tools.py
OptiHPLCHandler/applications/method_converter/method_converter.py
OptiHPLCHandler/applications/method_generators/add_isocratic_segment.py
OptiHPLCHandler/applications/method_generators/alter_strong_eluent_pct.py
OptiHPLCHandler/applications/method_generators/alter_temperature.py
OptiHPLCHandler/applications/method_generators/condense_gradient_table.py
OptiHPLCHandler/applications/method_generators/ramp_method.py
OptiHPLCHandler/plotting/gradient_plot.py
OptiHPLCHandler/plotting/gradient_utils.py
OptiHPLCHandler/utils/__init__.py
OptiHPLCHandler/utils/data_types.py
OptiHPLCHandler/utils/default_data.py
OptiHPLCHandler/utils/validate_gradient_table.py
OptiHPLCHandler/utils/validate_method_name.py
opti_hplc_handler-4.1.1.dist-info/licenses/LICENSE
opti_hplc_handler-4.1.1.dist-info/METADATA
opti_hplc_handler-4.1.1.dist-info/WHEEL
opti_hplc_handler-4.1.1.dist-info/top_level.txt
opti_hplc_handler-4.1.1.dist-info/RECORD
