Metadata-Version: 2.4
Name: Opti_HPLC_Handler
Version: 4.1.1
Summary: SDK for interacting with the Waters Empower Web API.
Author-email: Søren Furbo <srfu@novonordisk.com>
License: BSD 3-Clause License
Project-URL: Repository, https://github.com/novonordisk-research/OptiHPLCHandler.git
Classifier: Development Status :: 5 - Production/Stable
Classifier: Intended Audience :: Developers
Classifier: Intended Audience :: Science/Research
Classifier: License :: OSI Approved :: BSD License
Classifier: Operating System :: OS Independent
Classifier: Programming Language :: Python :: 3
Classifier: Programming Language :: Python :: 3.9
Classifier: Programming Language :: Python :: 3.10
Classifier: Programming Language :: Python :: 3.11
Classifier: Programming Language :: Python :: 3.12
Classifier: Topic :: Scientific/Engineering :: Chemistry
Classifier: Topic :: Software Development :: Libraries :: Python Modules
Requires-Python: >=3.9
License-File: LICENSE
Requires-Dist: keyring>=24.0.0
Requires-Dist: requests>=2.28.1
Provides-Extra: dev
Requires-Dist: black==23.3.0; extra == "dev"
Requires-Dist: black[jupyter]==23.3.0; extra == "dev"
Requires-Dist: flake8==7.0.0; extra == "dev"
Requires-Dist: isort==5.12.0; extra == "dev"
Provides-Extra: test
Requires-Dist: pytest==8.0.0; extra == "test"
Requires-Dist: pytest-cov==4.1.0; extra == "test"
Requires-Dist: numpy==1.26.1; extra == "test"
Provides-Extra: lint
Requires-Dist: black[jupyter]==23.3.0; extra == "lint"
Requires-Dist: flake8==7.0.0; extra == "lint"
Requires-Dist: isort==5.12.0; extra == "lint"
Provides-Extra: release
Requires-Dist: bumpver==2023.1125; extra == "release"
Provides-Extra: build
Requires-Dist: build==1.0.3; extra == "build"
Provides-Extra: doc
Requires-Dist: pylint==3.0.2; extra == "doc"
Requires-Dist: sphinx==7.2.6; extra == "doc"
Provides-Extra: examples
Requires-Dist: python-dotenv==1.0.1; extra == "examples"
Dynamic: license-file
